nonebot_plugin_a2s_query/__init__.py
nonebot_plugin_a2s_query-0.2.0.dist-info/LICENSE
nonebot_plugin_a2s_query-0.2.0.dist-info/METADATA
nonebot_plugin_a2s_query-0.2.0.dist-info/WHEEL
nonebot_plugin_a2s_query-0.2.0.dist-info/RECORD
