Metadata-Version: 2.1
Name: nonebot-plugin-a2s-query
Version: 0.2.0
Summary: a2s查询游戏服务器详情
Home-page: https://github.com/NanakaNeko/nonebot-plugin-a2s-query
License: MIT
Keywords: nonebot2,plugin,a2s,qq,bot
Author: 奈
Author-email: flneko@163.com
Requires-Python: >=3.9,<4.0
Classifier: License :: OSI Approved :: MIT License
Classifier: Programming Language :: Python :: 3
Classifier: Programming Language :: Python :: 3.9
Classifier: Programming Language :: Python :: 3.10
Classifier: Programming Language :: Python :: 3.11
Classifier: Programming Language :: Python :: 3.12
Requires-Dist: nonebot-adapter-onebot (>=2.1.0,<3.0.0)
Requires-Dist: nonebot-plugin-localstore (>=0.6.0,<0.7.0)
Requires-Dist: nonebot-plugin-txt2img (>=0.4.1,<0.5.0)
Requires-Dist: nonebot2 (>=2.0.0,<3.0.0)
Requires-Dist: pathlib (>=1.0.1,<2.0.0)
Requires-Dist: python-a2s (>=1.3.0,<2.0.0)
Requires-Dist: tabulate (>=0.9.0,<0.10.0)
Requires-Dist: ujson (>=5.9.0,<6.0.0)
Requires-Dist: wcwidth (>=0.2.13,<0.3.0)
Project-URL: Repository, https://github.com/NanakaNeko/nonebot-plugin-a2s-query
